kuryr/__init__.py
kuryr/cmd/__init__.py
kuryr/cmd/status.py
kuryr/lib/__init__.py
kuryr/lib/_i18n.py
kuryr/lib/config.py
kuryr/lib/constants.py
kuryr/lib/exceptions.py
kuryr/lib/opts.py
kuryr/lib/utils.py
kuryr/lib/version.py
kuryr/lib/binding/__init__.py
kuryr/lib/binding/drivers/__init__.py
kuryr/lib/binding/drivers/hw_veb.py
kuryr/lib/binding/drivers/ipvlan.py
kuryr/lib/binding/drivers/macvlan.py
kuryr/lib/binding/drivers/nested.py
kuryr/lib/binding/drivers/utils.py
kuryr/lib/binding/drivers/veth.py
kuryr/lib/binding/drivers/vlan.py
kuryr/lib/segmentation_type_drivers/__init__.py
kuryr/lib/segmentation_type_drivers/vlan.py
kuryr/tests/__init__.py
kuryr/tests/unit/__init__.py
kuryr/tests/unit/base.py
kuryr/tests/unit/test_config.py
kuryr/tests/unit/test_opts.py
kuryr/tests/unit/test_utils.py
kuryr/tests/unit/binding/__init__.py
kuryr/tests/unit/binding/drivers/__init__.py
kuryr/tests/unit/binding/drivers/test_hw_veb.py
kuryr/tests/unit/binding/drivers/test_ipvlan.py
kuryr/tests/unit/binding/drivers/test_macvlan.py
kuryr/tests/unit/binding/drivers/test_nested.py
kuryr/tests/unit/binding/drivers/test_utils.py
kuryr/tests/unit/binding/drivers/test_veth.py
kuryr/tests/unit/binding/drivers/test_vlan.py
kuryr/tests/unit/cmd/__init__.py
kuryr/tests/unit/cmd/test_status.py
kuryr/tests/unit/segmentation_type_drivers/__init__.py
kuryr/tests/unit/segmentation_type_drivers/test_vlan.py
kuryr_lib-3.4.0.data/data/libexec/kuryr/bridge
kuryr_lib-3.4.0.data/data/libexec/kuryr/iovisor
kuryr_lib-3.4.0.data/data/libexec/kuryr/midonet
kuryr_lib-3.4.0.data/data/libexec/kuryr/ovs
kuryr_lib-3.4.0.data/data/libexec/kuryr/tap
kuryr_lib-3.4.0.data/data/libexec/kuryr/unbound
kuryr_lib-3.4.0.dist-info/licenses/AUTHORS
kuryr_lib-3.4.0.dist-info/licenses/LICENSE
kuryr_lib-3.4.0.dist-info/METADATA
kuryr_lib-3.4.0.dist-info/WHEEL
kuryr_lib-3.4.0.dist-info/entry_points.txt
kuryr_lib-3.4.0.dist-info/pbr.json
kuryr_lib-3.4.0.dist-info/top_level.txt
kuryr_lib-3.4.0.dist-info/RECORD
