Metadata-Version: 2.4
Name: kuryr-lib
Version: 3.4.0
Summary: Kuryr shared config and utilities
Home-page: https://docs.openstack.org/kuryr/latest/
Author: OpenStack
Author-email: openstack-discuss@lists.openstack.org
Classifier: Environment :: OpenStack
Classifier: Intended Audience :: Information Technology
Classifier: Intended Audience :: System Administrators
Classifier: License :: OSI Approved :: Apache Software License
Classifier: Operating System :: POSIX :: Linux
Classifier: Programming Language :: Python
Classifier: Programming Language :: Python :: Implementation :: CPython
Classifier: Programming Language :: Python :: 3 :: Only
Classifier: Programming Language :: Python :: 3
Classifier: Programming Language :: Python :: 3.8
Classifier: Programming Language :: Python :: 3.9
Classifier: Programming Language :: Python :: 3.10
Classifier: Programming Language :: Python :: 3.11
Requires-Python: >=3.8
License-File: LICENSE
License-File: AUTHORS
Requires-Dist: Babel!=2.4.0,>=2.3.4
Requires-Dist: keystoneauth1>=3.4.0
Requires-Dist: neutron-lib>=1.13.0
Requires-Dist: oslo.concurrency>=3.25.0
Requires-Dist: oslo.i18n>=3.15.3
Requires-Dist: oslo.log>=3.36.0
Requires-Dist: oslo.upgradecheck>=0.1.0
Requires-Dist: oslo.utils>=3.33.0
Requires-Dist: pbr!=2.1.0,>=2.0.0
Requires-Dist: python-neutronclient>=6.7.0
Requires-Dist: pyroute2>=0.5.6; sys_platform != "win32"
Dynamic: author
Dynamic: author-email
Dynamic: classifier
Dynamic: description
Dynamic: home-page
Dynamic: license-file
Dynamic: provides-extra
Dynamic: requires-dist
Dynamic: requires-python
Dynamic: summary
